coreason_manifest/__init__.py
coreason_manifest/definitions/__init__.py
coreason_manifest/definitions/agent.py
coreason_manifest/definitions/audit.py
coreason_manifest/definitions/events.py
coreason_manifest/definitions/message.py
coreason_manifest/definitions/simulation.py
coreason_manifest/definitions/topology.py
coreason_manifest/recipes.py
coreason_manifest/schemas/__init__.py
coreason_manifest/schemas/agent.schema.json
coreason_manifest/utils/__init__.py
coreason_manifest/utils/logger.py
coreason_manifest-0.9.0.dist-info/METADATA
coreason_manifest-0.9.0.dist-info/WHEEL
coreason_manifest-0.9.0.dist-info/licenses/LICENSE
coreason_manifest-0.9.0.dist-info/licenses/NOTICE
coreason_manifest-0.9.0.dist-info/RECORD
