Metadata-Version: 2.4
Name: coreason_manifest
Version: 0.9.0
Summary: This package is the definitive source of truth. If it isn't in the manifest, it doesn't exist. If it violates the manifest, it doesn't run.
License: # The Prosperity Public License 3.0.0
License-File: LICENSE
License-File: NOTICE
Author: Gowtham A Rao
Author-email: gowtham.rao@coreason.ai
Requires-Python: >=3.12
Classifier: License :: Other/Proprietary License
Classifier: Programming Language :: Python :: 3.12
Classifier: Operating System :: OS Independent
Requires-Dist: coreason-identity (>=0.4.1,<0.5.0)
Requires-Dist: loguru (>=0.7.2,<0.8.0)
Requires-Dist: pydantic (>=2.12.5,<3.0.0)
Requires-Dist: pyyaml (>=6.0.3,<7.0.0)
Project-URL: Documentation, https://github.com/CoReason-AI/coreason_manifest
Project-URL: Homepage, https://github.com/CoReason-AI/coreason_manifest
Project-URL: Repository, https://github.com/CoReason-AI/coreason_manifest
